asciicolor/__init__.py
asciicolor-1.5.dist-info/METADATA
asciicolor-1.5.dist-info/WHEEL
asciicolor-1.5.dist-info/top_level.txt
asciicolor-1.5.dist-info/RECORD
