Metadata-Version: 2.1
Name: asciicolor
Version: 1.5
Summary: python3 package to colors your output
Author-email: rootcli53@gmail.com
License: Eclipse Public License 2.0
